fp_ngfw_smc_python-1.0.32.dist-info/licenses/LICENSE
smc/.gitignore
smc/__init__.py
smc/__version__.py
smc/compat.py
smc/known_issues
smc/actions/__init__.py
smc/administration/__init__.py
smc/administration/access_rights.py
smc/administration/eca_client_config.py
smc/administration/filter.py
smc/administration/license.py
smc/administration/monitoring_status.py
smc/administration/reports.py
smc/administration/role.py
smc/administration/scheduled_tasks.py
smc/administration/system.py
smc/administration/system_properties.py
smc/administration/tasks.py
smc/administration/upcoming_event.py
smc/administration/updates.py
smc/administration/certificates/__init__.py
smc/administration/certificates/certificate_authority.py
smc/administration/certificates/tls.py
smc/administration/certificates/tls_common.py
smc/administration/certificates/vpn.py
smc/administration/user_auth/__init__.py
smc/administration/user_auth/servers.py
smc/administration/user_auth/users.py
smc/api/__init__.py
smc/api/common.py
smc/api/configloader.py
smc/api/entry_point.py
smc/api/exceptions.py
smc/api/session.py
smc/api/web.py
smc/base/__init__.py
smc/base/collection.py
smc/base/decorators.py
smc/base/mixins.py
smc/base/model.py
smc/base/structs.py
smc/base/util.py
smc/core/__init__.py
smc/core/addon.py
smc/core/advanced_settings.py
smc/core/collection.py
smc/core/contact_address.py
smc/core/engine.py
smc/core/engine_vss.py
smc/core/engines.py
smc/core/external_pki.py
smc/core/general.py
smc/core/ha_management.py
smc/core/hardware.py
smc/core/interfaces.py
smc/core/lldp.py
smc/core/node.py
smc/core/policy.py
smc/core/resource.py
smc/core/route.py
smc/core/session_monitoring.py
smc/core/sub_interfaces.py
smc/core/waiters.py
smc/docs/.gitignore
smc/docs/Makefile
smc/docs/conf.py
smc/docs/index.rst
smc/docs/requirements.txt
smc/docs/pages/administration.rst
smc/docs/pages/collections.rst
smc/docs/pages/elements.rst
smc/docs/pages/engine.rst
smc/docs/pages/extensions.rst
smc/docs/pages/installation.rst
smc/docs/pages/intro.rst
smc/docs/pages/logging.rst
fp_ngfw_smc_python-1.0.32.dist-info/METADATA
fp_ngfw_smc_python-1.0.32.dist-info/WHEEL
fp_ngfw_smc_python-1.0.32.dist-info/top_level.txt
fp_ngfw_smc_python-1.0.32.dist-info/RECORD
