Metadata-Version: 2.4
Name: fp-NGFW-SMC-python
Version: 1.0.32
Summary: Python based API to Forcepoint NGFW Management Center
Author-email: Forcepoint <PSIRT@forcepoint.com>
License: Apache License (2.0)
Classifier: Development Status :: 5 - Production/Stable
Classifier: Programming Language :: Python
Classifier: Programming Language :: Python :: 3
Requires-Python: >=3.5
License-File: LICENSE
Requires-Dist: requests>=2.31.0
Requires-Dist: pytz>=2022.6
Requires-Dist: urllib3>=1.26.18
Dynamic: license-file
